paymongo/__init__.py
paymongo/api_resources/__init__.py
paymongo/api_resources/api_resource.py
paymongo/api_resources/paymongo_client.py
paymongo/api_resources/paymongo_config.py
paymongo/api_resources/paymongo_error.py
paymongo/api_resources/entities/__init__.py
paymongo/api_resources/entities/base_entity.py
paymongo/api_resources/entities/billing_address_entity.py
paymongo/api_resources/entities/billing_entity.py
paymongo/api_resources/entities/customer_entity.py
paymongo/api_resources/entities/event_entity.py
paymongo/api_resources/entities/link_entity.py
paymongo/api_resources/entities/listing_entity.py
paymongo/api_resources/entities/payment_entity.py
paymongo/api_resources/entities/payment_intent_entity.py
paymongo/api_resources/entities/payment_method_entity.py
paymongo/api_resources/entities/refund_entity.py
paymongo/api_resources/entities/webhook_entity.py
paymongo/api_resources/exceptions/__init__.py
paymongo/api_resources/exceptions/authentication_exception.py
paymongo/api_resources/exceptions/invalid_request_exception.py
paymongo/api_resources/exceptions/resource_not_found_exception.py
paymongo/api_resources/exceptions/signature_verification_exception.py
paymongo/api_resources/exceptions/standard_exception.py
paymongo/api_resources/exceptions/unexpected_value_exception.py
paymongo/api_resources/services/__init__.py
paymongo/api_resources/services/base_service.py
paymongo/api_resources/services/customer.py
paymongo/api_resources/services/link.py
paymongo/api_resources/services/payment.py
paymongo/api_resources/services/payment_intent.py
paymongo/api_resources/services/payment_method.py
paymongo/api_resources/services/refund.py
paymongo/api_resources/services/webhook.py
paymongo_python-0.1.0.dist-info/LICENSE
paymongo_python-0.1.0.dist-info/METADATA
paymongo_python-0.1.0.dist-info/WHEEL
paymongo_python-0.1.0.dist-info/top_level.txt
paymongo_python-0.1.0.dist-info/RECORD
