Metadata-Version: 2.1
Name: paymongo-python
Version: 0.1.0
Summary: PayMongo Python Library
Home-page: https://github.com/paymongo/paymongo-python
Author: PayMongo
Author-email: support@paymongo.com
License: MIT
Keywords: paymongo
Classifier: Development Status :: 4 - Beta
Classifier: Intended Audience :: Developers
Classifier: Operating System :: Microsoft :: Windows :: Windows 10
Classifier: License :: OSI Approved :: MIT License
Classifier: Programming Language :: Python :: 3
License-File: LICENSE
Requires-Dist: requests
